mock_mcp_server/__init__.py
mock_mcp_server/main.py
mock_mcp_server-0.1.1.dist-info/METADATA
mock_mcp_server-0.1.1.dist-info/WHEEL
mock_mcp_server-0.1.1.dist-info/entry_points.txt
mock_mcp_server-0.1.1.dist-info/licenses/LICENSE
mock_mcp_server-0.1.1.dist-info/RECORD
