Metadata-Version: 2.4
Name: mock-mcp-server
Version: 0.1.1
Summary: A mock MCP server for testing
Author-email: DiscreteTom <discrete_tom@outlook.com>
License: MIT
License-File: LICENSE
Keywords: mcp,mock,server,testing
Classifier: Development Status :: 3 - Alpha
Classifier: Intended Audience :: Developers
Classifier: License :: OSI Approved :: MIT License
Classifier: Programming Language :: Python :: 3
Classifier: Programming Language :: Python :: 3.10
Classifier: Programming Language :: Python :: 3.11
Classifier: Programming Language :: Python :: 3.12
Classifier: Programming Language :: Python :: 3.13
Requires-Python: >=3.10
Requires-Dist: fastmcp>=2.13.0.2
Requires-Dist: typer>=0.20.0
